{
  "version": 23,
  "languages": [
    0,
    1,
    2,
    3,
    4,
    5,
    6,
    7,
    -1,
    -1,
    10,
    11,
    12,
    13,
    -1,
    -1,
    -1,
    -1,
    -1,
    -1,
    -1,
    21,
    -1,
    -1,
    -1,
    -1,
    26,
    -1,
    -1,
    -1,
    -1,
    -1,
    32
  ],
  "attribute_headers": [],
  "entries": [
    {
      "name": "Mission508010_000",
      "guid": "bf4ad46d-ba8a-4d93-96ab-3e715039a2a0",
      "crc?": 3851895427,
      "hash": 3332775346,
      "attributes": [],
      "content": [
        "諍いの果てに",
        "Continuing Conflict",
        "Conflit incessant",
        "Conflitto continuo",
        "Fortlaufender Konflikt",
        "Conflicto continuado",
        "Непрекращающийся конфликт",
        "Trwający konflikt",
        "",
        "",
        "Conflito Contínuo",
        "싸움 끝에",
        "鬥爭的盡頭",
        "两怪相争",
        "",
        "",
        "",
        "",
        "",
        "",
        "",
        "صراع مستمر",
        "",
        "",
        "",
        "",
        "ความขัดแย้งไม่รู้จบ",
        "",
        "",
        "",
        "",
        "",
        "Conflicto continuado"
      ]
    },
    {
      "name": "Mission508010_001",
      "guid": "f5cdf0ea-f5ab-4da4-b68b-e63dca97e5e0",
      "crc?": 118260342,
      "hash": 627520874,
      "attributes": [],
      "content": [
        "ムタバの話によれば、クナファ村の近くで\r\n２頭のモンスターが争っているのだという。\r\nそれは数日間おさまらず、このままではいつ\r\n村の者が巻き込まれてもおかしくはない。\r\n現地調査を行い、必要であれば何かしらの\r\n対処が必要だろう。",
        "Murtabak reported two monsters fighting\r\nnear Kunafa. It has been going on for\r\ndays, and if left alone, could pose a \r\ndanger to the villagers. Go investigate,\r\nand take the necessary measures to\r\nensure the safety of the village.",
        "Murtabak a vu deux monstres se battre près\r\nde Kunafa. Le combat dure depuis des jours\r\net les villageois seront en danger si rien n'est\r\nfait. Allez voir sur place et faites ce qu'il faut\r\npour protéger le village.",
        "Murtabak ha riferito che ci sono due\r\nmostri che combattono vicino a Kunafa.\r\nLa situazione continua da due giorni\r\ne, se nessuno interviene, costituirà un\r\npericolo per gli abitanti. Vai a\r\nindagare e fai il necessario per\r\ngarantire la sicurezza del villaggio.",
        "Laut Murtabak kämpfen nahe Kunafa schon\r\nseit Tagen zwei Monster. Lässt man sie ge-\r\nwähren, werden sie früher oder später zur\r\nGefahr für die Dorfbewohner. Untersuche\r\ndie Situation und unternimm alle nötigen\r\nMaßnahmen, um das Dorf zu schützen.",
        "Murtabak nos ha hecho saber que hay\r\ndos monstruos peleando cerca de Kunafa.\r\nLlevan días así, y podrían suponer un\r\npeligro para los aldeanos. Ve a\r\ninvestigar y toma medidas para\r\nla seguridad de la aldea.",
        "Муртабак сообщает о том, что около\r\nКунафы сцепились два монстра. Они\r\nсражаются уже несколько дней, и, если не\r\nвмешаться, могут пострадать местные\r\nжители. Необходимо принять меры, чтобы\r\nобеспечить безопасность деревни.",
        "Murtabak zgłosił walkę dwóch potworów \r\nw pobliżu Kunafy. Konflikt trwa już od \r\nkilku dni i jeśli zostanie pozostawiony \r\nsam sobie, będzie stanowić zagrożenie \r\ndla mieszkańców wioski. Zbadaj \r\nsprawę i podejmij niezbędne środki, \r\naby zapewnić bezpieczeństwo wiosce.",
        "",
        "",
        "Murtabak relatou que dois monstros\r\nestão lutando perto de Kunafa. Eles\r\nestão brigando há dias, se nada for\r\nfeito, os aldeões podem ser afetados.\r\nVá investigar e tome as medidas\r\nnecessárias para garantir a segurança\r\nda aldeia.",
        "무타바에 의하면 쿠나파 마을 근처에서\r\n두 몬스터가 싸우고 있다고 한다.\r\n싸움은 며칠씩 이어졌고, 이대로 두면\r\n마을 사람이 휘말릴 수도 있다.\r\n현지를 조사하고, 필요하다면\r\n상황에 맞게 대처해야 한다.",
        "聽穆塔巴說，庫納法村附近有兩頭魔物一直在\r\n打鬥，過了好幾天還沒有停下來。這樣下去\r\n隨時會牽連到村民，所以需要到現場調查，\r\n必要時要採取相應對策。",
        "据穆塔帕说，库纳法村附近有两头怪物正在\r\n激烈争斗，数日来毫无停歇的迹象。若任由\r\n事态发展，恐怕村里的居民也会受到波及。\r\n因此，请前往现场进行调查，必要时采取应\r\n对措施。",
        "",
        "",
        "",
        "",
        "",
        "",
        "",
        "أبلغ (مورتاباك) عن وحشين يتناحران\r\nبالقرب من (كُنافة). استمر ذلك\r\nلأيام وإن تُرك الأمر على حاله\r\nفسيكون خطرًا على القرويين.\r\nلذا <LSNR \"اذهب واستقصى واتخذ\" \"اذهبي واستقصي واتخذي\">\r\nالتدابير اللازمة لضمان سلامة القرويين.",
        "",
        "",
        "",
        "",
        "มูร์ตาบักรายงานว่ามีมอนสเตอร์สองตัวสู้กัน\r\nใกล้กับคูนาฟา ซึ่งยือเยื้อมานานหลายวันแล้ว\r\nและถ้าไม่มีคนไปจัดการ ก็อาจเป็นอันตราย\r\nกับชาวบ้านได้ ไปตรวจสอบเรื่องนี้และจัดการ\r\nตามที่จำเป็นเพื่อทำให้หมู่บ้านปลอดภัย",
        "",
        "",
        "",
        "",
        "",
        "Murtabak informó sobre una lucha entre\r\ndos monstruos cerca de Kunafa. Llevan\r\ndías así, pero dejarlos solos supondría\r\nun peligro para los aldeanos.\r\nVe a investigar y toma las medidas\r\nnecesarias para garantizar la seguridad\r\nde la aldea."
      ]
    },
    {
      "name": "Mission508010_010",
      "guid": "96a5788c-d1db-47bf-b141-02967b72a34a",
      "crc?": 1608044753,
      "hash": 3801270963,
      "attributes": [],
      "content": [
        "同名のフリークエストを受注する",
        "Accept the Optional Quest",
        "Accepter la quête libre",
        "Accetta la missione facoltativa",
        "Nimm die Optionale Quest an.",
        "Acepta la misión opcional",
        "Примите это доп. поручение",
        "Przyjmij zadanie opcjonalne",
        "",
        "",
        "Aceite a Missão Opcional",
        "같은 명칭의 자유 퀘스트 수주하기",
        "承接同名的自由任務",
        "承接同名的自由任务",
        "",
        "",
        "",
        "",
        "",
        "",
        "",
        "قبول المَهمة الاختيارية",
        "",
        "",
        "",
        "",
        "ตอบรับเควสต์เสริม",
        "",
        "",
        "",
        "",
        "",
        "Acepta la misión opcional"
      ]
    },
    {
      "name": "Mission508010_011",
      "guid": "2f54a003-b092-4d23-8687-72afc14e3321",
      "crc?": 2555475359,
      "hash": 3689091915,
      "attributes": [],
      "content": [
        "<REF NpcName_NN_35>に報告する",
        "Report to <REF NpcName_NN_35>",
        "Parler à <REF NpcName_NN_35>",
        "Fai rapporto a <REF NpcName_NN_35>",
        "Sprich mit <REF NpcName_NN_35>.",
        "Habla con <REF NpcName_NN_35>",
        "Вернитесь к Муртабаку",
        "Zgłoś się do: <REF NpcName_NN_35>",
        "",
        "",
        "Fale com <REF NpcName_NN_35>",
        "<REF NpcName_NN_35>에게 보고하기",
        "向<REF NpcName_NN_35>報告",
        "向<REF NpcName_NN_35>报告",
        "",
        "",
        "",
        "",
        "",
        "",
        "",
        "إبلاغ <REF NpcName_NN_35>",
        "",
        "",
        "",
        "",
        "รายงาน<REF NpcName_NN_35>",
        "",
        "",
        "",
        "",
        "",
        "Informa a <REF NpcName_NN_35>"
      ]
    }
  ]
}