[
  {
    "app.snd_user_data.SoundMusicEm0078_00ParamData": {
      "_PhaseStateList": [
        {
          "soundlib.SoundStateInfo": {
            "_StateGroupId": 1829731616,
            "_StateId": 3630028971
          }
        },
        {
          "soundlib.SoundStateInfo": {
            "_StateGroupId": 1829731616,
            "_StateId": 3630028968
          }
        }
      ],
      "_OnHitRailgunTriggerId": 4294967295,
      "_SetStateTimeAfterRailgun": 3.0,
      "_RailgunStateList": [
        {
          "soundlib.SoundStateInfo": {
            "_StateGroupId": 3311390558,
            "_StateId": 930712164
          }
        },
        {
          "soundlib.SoundStateInfo": {
            "_StateGroupId": 3311390558,
            "_StateId": 1651971902
          }
        }
      ],
      "_SetStateTimeAfterLastResort": 5.0,
      "_LastResortStateList": [
        {
          "soundlib.SoundStateInfo": {
            "_StateGroupId": 3369784610,
            "_StateId": 1651971902
          }
        },
        {
          "soundlib.SoundStateInfo": {
            "_StateGroupId": 4294967295,
            "_StateId": 4294967295
          }
        },
        {
          "soundlib.SoundStateInfo": {
            "_StateGroupId": 3982097962,
            "_StateId": 1651971902
          }
        },
        {
          "soundlib.SoundStateInfo": {
            "_StateGroupId": 3369784610,
            "_StateId": 930712164
          }
        }
      ]
    }
  }
]