[
  {
    "app.user_data.Gm407Data": {
      "_WaitFrontPointList_High": [
        {
          "app.user_data.Gm407Data.cLinkedPoint": {
            "_Pos": [
              921.75,
              -104.1389,
              -38.5147,
              0.0
            ],
            "_DegY": -115,
            "_Pos2": [
              924.1304,
              -174.9779,
              -37.2923,
              0.0
            ],
            "_DegY2": 55
          }
        },
        {
          "app.user_data.Gm407Data.cLinkedPoint": {
            "_Pos": [
              922.2313,
              -104.2653,
              -37.6652,
              0.0
            ],
            "_DegY": -115,
            "_Pos2": [
              923.9498,
              -175.0019,
              -36.5786,
              0.0
            ],
            "_DegY2": 55
          }
        },
        {
          "app.user_data.Gm407Data.cLinkedPoint": {
            "_Pos": [
              922.4879,
              -104.218,
              -38.8407,
              0.0
            ],
            "_DegY": -115,
            "_Pos2": [
              924.9008,
              -175.0723,
              -37.5739,
              0.0
            ],
            "_DegY2": 55
          }
        }
      ],
      "_WaitFrontPointList_Low": [
        {
          "app.user_data.Gm407Data.cLinkedPoint": {
            "_Pos": [
              923.9269,
              -174.0999,
              -41.2609,
              0.0
            ],
            "_DegY": -125,
            "_Pos2": [
              923.7105,
              -104.1202,
              -41.5564,
              0.0
            ],
            "_DegY2": 55
          }
        },
        {
          "app.user_data.Gm407Data.cLinkedPoint": {
            "_Pos": [
              923.7764,
              -174.1952,
              -40.6472,
              0.0
            ],
            "_DegY": -125,
            "_Pos2": [
              923.4429,
              -104.132,
              -41.1827,
              0.0
            ],
            "_DegY2": 55
          }
        },
        {
          "app.user_data.Gm407Data.cLinkedPoint": {
            "_Pos": [
              924.4186,
              -174.1565,
              -41.7076,
              0.0
            ],
            "_DegY": -125,
            "_Pos2": [
              923.941,
              -104.1449,
              -42.0142,
              0.0
            ],
            "_DegY2": 55
          }
        }
      ],
      "_WaitBehindPointList_High": [
        {
          "app.user_data.Gm407Data.cPoint": {
            "_Pos": [
              923.7865,
              -104.7688,
              -36.3149,
              0.0
            ],
            "_DegY": -125
          }
        },
        {
          "app.user_data.Gm407Data.cPoint": {
            "_Pos": [
              925.3788,
              -104.9169,
              -37.1877,
              0.0
            ],
            "_DegY": -115
          }
        }
      ],
      "_WaitBehindPointList_Low": [
        {
          "app.user_data.Gm407Data.cPoint": {
            "_Pos": [
              926.995,
              -175.3459,
              -38.599,
              0.0
            ],
            "_DegY": -120
          }
        },
        {
          "app.user_data.Gm407Data.cPoint": {
            "_Pos": [
              928.5384,
              -175.644,
              -38.769,
              0.0
            ],
            "_DegY": -120
          }
        }
      ],
      "STRUCT__OwLiftHeightOffsetRange_Up_GetOn__HasValue": true,
      "STRUCT__OwLiftHeightOffsetRange_Up_GetOn__Value": {
        "raw": "3d0ad73e6966e63e",
        "type": "Range"
      },
      "STRUCT__OwLiftHeightOffsetRange_Up_GetOff__HasValue": true,
      "STRUCT__OwLiftHeightOffsetRange_Up_GetOff__Value": {
        "raw": "cdcc4cbd33335340",
        "type": "Range"
      },
      "STRUCT__OwLiftHeightOffsetRange_Down_GetOn__HasValue": false,
      "STRUCT__OwLiftHeightOffsetRange_Down_GetOn__Value": {
        "raw": "0000000000000000",
        "type": "Range"
      },
      "STRUCT__OwLiftHeightOffsetRange_Down_GetOff__HasValue": true,
      "STRUCT__OwLiftHeightOffsetRange_Down_GetOff__Value": {
        "raw": "6666e6bf00004040",
        "type": "Range"
      },
      "_InteractMotionFrame_GetOn_Low": 748,
      "_InteractMotionFrame_GetOff_Low": 1162
    }
  }
]