[
  {
    "ace.user_data.ModelMaterialInfo": {
      "_Conditions": [
        {
          "ace.model_material_manager.cConditionInfo": {
            "_ConditionId": "af6a74d5-a267-49f4-bf78-ebe514bef0ad",
            "_MaterialParameters": [
              {
                "ace.model_material_manager.cMaterialParameterInfo": {
                  "_Id": "c92828a7-7a21-43b9-8d0c-fb7e049df1a3",
                  "_Enable": true,
                  "_MaterialNameHashList": [
                    3287661546,
                    2019561304,
                    146801443,
                    2564175767
                  ],
                  "_ParameterNameHash": 365752137,
                  "_ParameterChannel": -1,
                  "_VariableType": 4,
                  "_Value": {
                    "app.model_material_manager.cValueColorRandomPreview": {
                      "app.model_material_manager.CororRandomResource": {
                        "_UserCurve": "Art/Model/Character/ch91/023/0000/ch91_023_0000_ColorParam.ucurve"
                      }
                    }
                  },
                  "_BeforeInterpolationInfo": {
                    "ace.model_material_manager.cInterpolationInfo": {
                      "_Frame": 0.0
                    }
                  }
                }
              },
              {
                "ace.model_material_manager.cMaterialParameterInfo": {
                  "_Id": "285ca4e2-c295-4325-8abf-9e4dca90c57e",
                  "_Enable": true,
                  "_MaterialNameHashList": [
                    3955769304,
                    1797513827,
                    4251657167
                  ],
                  "_ParameterNameHash": 365752137,
                  "_ParameterChannel": -1,
                  "_VariableType": 4,
                  "_Value": {
                    "app.model_material_manager.cValueColorPickerRandom": {
                      "app.model_material_manager.CororPickerRandomResource": {
                        "_InterpolateType": 0,
                        "_Color1": [
                          0.0
                        ],
                        "_Color2": [
                          0.0
                        ]
                      }
                    }
                  },
                  "_BeforeInterpolationInfo": {
                    "ace.model_material_manager.cInterpolationInfo": {
                      "_Frame": 0.0
                    }
                  }
                }
              }
            ]
          }
        },
        {
          "ace.model_material_manager.cConditionInfo": {
            "_ConditionId": "f289f813-99e3-4310-872d-f728596aa94f",
            "_MaterialParameters": []
          }
        },
        {
          "ace.model_material_manager.cConditionInfo": {
            "_ConditionId": "de65436d-10a6-4c9f-bbc7-4772246249f7",
            "_MaterialParameters": []
          }
        },
        {
          "ace.model_material_manager.cConditionInfo": {
            "_ConditionId": "0e127ca0-15ef-44cb-afd4-b0155a0087fd",
            "_MaterialParameters": []
          }
        },
        {
          "ace.model_material_manager.cConditionInfo": {
            "_ConditionId": "72e70094-0c10-4090-8408-acfac6647104",
            "_MaterialParameters": []
          }
        },
        {
          "ace.model_material_manager.cConditionInfo": {
            "_ConditionId": "9dd47cfa-9bc7-4e57-a585-b929a6849b16",
            "_MaterialParameters": []
          }
        },
        {
          "ace.model_material_manager.cConditionInfo": {
            "_ConditionId": "52daab5d-1578-460f-aebf-3d2aac2851ca",
            "_MaterialParameters": []
          }
        },
        {
          "ace.model_material_manager.cConditionInfo": {
            "_ConditionId": "fc3ad4d5-44a6-47a3-b9e5-284c427578c8",
            "_MaterialParameters": []
          }
        }
      ]
    }
  }
]