[
  {
    "app.user_data.NpcEmPartsData": {
      "_PartsData": {
        "app.user_data.EmParamParts": {
          "ref_instance_id": 1,
          "path": "GameDesign/Enemy/Em0166/00/Data/Em0166_00_Param_Parts.user"
        }
      },
      "_JointTable": "[0] NONE",
      "_DownTargetJoints": [
        {
          "ace.cStrHash": {
            "_Hash": 300621386
          }
        }
      ],
      "_ExtraTargetJoints": [
        {
          "ace.cStrHash": {
            "_Hash": 3127669525
          }
        },
        {
          "ace.cStrHash": {
            "_Hash": 2392863574
          }
        },
        {
          "ace.cStrHash": {
            "_Hash": 3763299385
          }
        },
        {
          "ace.cStrHash": {
            "_Hash": 3225589516
          }
        },
        {
          "ace.cStrHash": {
            "_Hash": 300621386
          }
        }
      ],
      "_ExtraAimAdjustTargetJoints": [
        {
          "ace.cStrHash": {
            "_Hash": 3127669525
          }
        },
        {
          "ace.cStrHash": {
            "_Hash": 2392863574
          }
        },
        {
          "ace.cStrHash": {
            "_Hash": 3763299385
          }
        },
        {
          "ace.cStrHash": {
            "_Hash": 3225589516
          }
        }
      ],
      "_MeatDataList": [
        {
          "app.user_data.NpcEmPartsData.cPartData": {
            "_PartGuid": "deff9aea-a485-4b43-aa78-e547f01239df",
            "_IsEnable": false,
            "_PriorityBlow": "[1] HIGH",
            "_PriorityBreak": false,
            "_PrioritySlash": false,
            "_IsEnable_UniqueSituation": [
              false,
              false,
              false
            ]
          }
        },
        {
          "app.user_data.NpcEmPartsData.cPartData": {
            "_PartGuid": "e2eb47d0-c319-411d-905b-98d91402150b",
            "_IsEnable": false,
            "_PriorityBlow": "[1] HIGH",
            "_PriorityBreak": false,
            "_PrioritySlash": false,
            "_IsEnable_UniqueSituation": [
              false,
              false,
              false
            ]
          }
        },
        {
          "app.user_data.NpcEmPartsData.cPartData": {
            "_PartGuid": "d1b36e45-ae15-4690-996c-ad9e58b1ef33",
            "_IsEnable": false,
            "_PriorityBlow": "[0] NONE",
            "_PriorityBreak": false,
            "_PrioritySlash": false,
            "_IsEnable_UniqueSituation": [
              false,
              false,
              false
            ]
          }
        },
        {
          "app.user_data.NpcEmPartsData.cPartData": {
            "_PartGuid": "a6df8ab0-4278-413e-8d99-87ca341f1422",
            "_IsEnable": false,
            "_PriorityBlow": "[1] HIGH",
            "_PriorityBreak": false,
            "_PrioritySlash": false,
            "_IsEnable_UniqueSituation": [
              false,
              false,
              false
            ]
          }
        },
        {
          "app.user_data.NpcEmPartsData.cPartData": {
            "_PartGuid": "1c6a25c6-b430-4c5b-83ea-47d9a2f8e5eb",
            "_IsEnable": true,
            "_PriorityBlow": "[1] HIGH",
            "_PriorityBreak": false,
            "_PrioritySlash": false,
            "_IsEnable_UniqueSituation": [
              false,
              true,
              true
            ]
          }
        },
        {
          "app.user_data.NpcEmPartsData.cPartData": {
            "_PartGuid": "cad44a0c-3d19-4531-ac04-d060ace8d87c",
            "_IsEnable": true,
            "_PriorityBlow": "[0] NONE",
            "_PriorityBreak": false,
            "_PrioritySlash": false,
            "_IsEnable_UniqueSituation": [
              true,
              false,
              true
            ]
          }
        },
        {
          "app.user_data.NpcEmPartsData.cPartData": {
            "_PartGuid": "dc623f64-e7d0-460d-a20c-f7a55f7e151d",
            "_IsEnable": true,
            "_PriorityBlow": "[0] NONE",
            "_PriorityBreak": false,
            "_PrioritySlash": false,
            "_IsEnable_UniqueSituation": [
              true,
              false,
              true
            ]
          }
        },
        {
          "app.user_data.NpcEmPartsData.cPartData": {
            "_PartGuid": "13bbbcbd-53e1-4747-8a22-4424f3549095",
            "_IsEnable": true,
            "_PriorityBlow": "[0] NONE",
            "_PriorityBreak": false,
            "_PrioritySlash": false,
            "_IsEnable_UniqueSituation": [
              false,
              false,
              false
            ]
          }
        },
        {
          "app.user_data.NpcEmPartsData.cPartData": {
            "_PartGuid": "79db2e4d-1da1-499a-a916-46ea7d1ab257",
            "_IsEnable": false,
            "_PriorityBlow": "[1] HIGH",
            "_PriorityBreak": false,
            "_PrioritySlash": false,
            "_IsEnable_UniqueSituation": [
              false,
              false,
              true
            ]
          }
        },
        {
          "app.user_data.NpcEmPartsData.cPartData": {
            "_PartGuid": "d8d08254-8a04-41e8-8549-9ddcfade284f",
            "_IsEnable": true,
            "_PriorityBlow": "[0] NONE",
            "_PriorityBreak": false,
            "_PrioritySlash": false,
            "_IsEnable_UniqueSituation": [
              false,
              false,
              false
            ]
          }
        },
        {
          "app.user_data.NpcEmPartsData.cPartData": {
            "_PartGuid": "8ea17ffe-3849-457c-b1b8-e4c6fe909726",
            "_IsEnable": true,
            "_PriorityBlow": "[0] NONE",
            "_PriorityBreak": false,
            "_PrioritySlash": false,
            "_IsEnable_UniqueSituation": [
              false,
              false,
              false
            ]
          }
        },
        {
          "app.user_data.NpcEmPartsData.cPartData": {
            "_PartGuid": "518600eb-6390-488e-a127-9531f3f84e3a",
            "_IsEnable": true,
            "_PriorityBlow": "[0] NONE",
            "_PriorityBreak": false,
            "_PrioritySlash": false,
            "_IsEnable_UniqueSituation": [
              false,
              false,
              false
            ]
          }
        },
        {
          "app.user_data.NpcEmPartsData.cPartData": {
            "_PartGuid": "b775f67c-cf93-4c7c-811d-395c623601be",
            "_IsEnable": true,
            "_PriorityBlow": "[0] NONE",
            "_PriorityBreak": false,
            "_PrioritySlash": false,
            "_IsEnable_UniqueSituation": []
          }
        },
        {
          "app.user_data.NpcEmPartsData.cPartData": {
            "_PartGuid": "fefb6d61-192d-4aa3-ace8-1fc3ae634e09",
            "_IsEnable": true,
            "_PriorityBlow": "[0] NONE",
            "_PriorityBreak": false,
            "_PrioritySlash": false,
            "_IsEnable_UniqueSituation": []
          }
        },
        {
          "app.user_data.NpcEmPartsData.cPartData": {
            "_PartGuid": "aea4f75f-6479-412f-a4f3-21c9f5c1d74c",
            "_IsEnable": true,
            "_PriorityBlow": "[0] NONE",
            "_PriorityBreak": false,
            "_PrioritySlash": false,
            "_IsEnable_UniqueSituation": []
          }
        },
        {
          "app.user_data.NpcEmPartsData.cPartData": {
            "_PartGuid": "09bc20c9-7330-4635-b4cf-22aa7951ddb2",
            "_IsEnable": true,
            "_PriorityBlow": "[0] NONE",
            "_PriorityBreak": false,
            "_PrioritySlash": false,
            "_IsEnable_UniqueSituation": []
          }
        },
        {
          "app.user_data.NpcEmPartsData.cPartData": {
            "_PartGuid": "a781ff5a-66d4-4edc-a090-2d1dbc38befd",
            "_IsEnable": true,
            "_PriorityBlow": "[0] NONE",
            "_PriorityBreak": false,
            "_PrioritySlash": false,
            "_IsEnable_UniqueSituation": []
          }
        },
        {
          "app.user_data.NpcEmPartsData.cPartData": {
            "_PartGuid": "092cff8e-9ae5-40fe-9bfa-cd644c4dad91",
            "_IsEnable": true,
            "_PriorityBlow": "[0] NONE",
            "_PriorityBreak": false,
            "_PrioritySlash": false,
            "_IsEnable_UniqueSituation": []
          }
        },
        {
          "app.user_data.NpcEmPartsData.cPartData": {
            "_PartGuid": "a9340985-d710-43ed-aa63-49d695f6d6b2",
            "_IsEnable": true,
            "_PriorityBlow": "[0] NONE",
            "_PriorityBreak": false,
            "_PrioritySlash": false,
            "_IsEnable_UniqueSituation": []
          }
        },
        {
          "app.user_data.NpcEmPartsData.cPartData": {
            "_PartGuid": "a1325e8c-8501-471b-8c76-183fbaee2aa1",
            "_IsEnable": true,
            "_PriorityBlow": "[0] NONE",
            "_PriorityBreak": false,
            "_PrioritySlash": false,
            "_IsEnable_UniqueSituation": []
          }
        },
        {
          "app.user_data.NpcEmPartsData.cPartData": {
            "_PartGuid": "7d46f128-561c-4480-9f01-69bae3318d9c",
            "_IsEnable": true,
            "_PriorityBlow": "[0] NONE",
            "_PriorityBreak": false,
            "_PrioritySlash": false,
            "_IsEnable_UniqueSituation": []
          }
        },
        {
          "app.user_data.NpcEmPartsData.cPartData": {
            "_PartGuid": "89376eaf-1f1e-4e45-8bdb-09d22e5b032c",
            "_IsEnable": true,
            "_PriorityBlow": "[0] NONE",
            "_PriorityBreak": false,
            "_PrioritySlash": false,
            "_IsEnable_UniqueSituation": []
          }
        },
        {
          "app.user_data.NpcEmPartsData.cPartData": {
            "_PartGuid": "c85c2b85-31dc-41f1-b1f4-4dd4001233a9",
            "_IsEnable": true,
            "_PriorityBlow": "[0] NONE",
            "_PriorityBreak": false,
            "_PrioritySlash": false,
            "_IsEnable_UniqueSituation": []
          }
        },
        {
          "app.user_data.NpcEmPartsData.cPartData": {
            "_PartGuid": "1e5644d7-9712-4fa9-a1bc-cf5755ce81ba",
            "_IsEnable": true,
            "_PriorityBlow": "[0] NONE",
            "_PriorityBreak": false,
            "_PrioritySlash": false,
            "_IsEnable_UniqueSituation": []
          }
        }
      ]
    }
  }
]