[
  {
    "app.user_data.DialogueMessage": {
      "_Values": [
        {
          "app.user_data.DialogueMessage.cData": {
            "_Index": 13,
            "_Voice": 0,
            "_AirouVoice": 0,
            "_MessageText": "00000000-0000-0000-0000-000000000000",
            "_MessageTextChoice": "a61a28a2-1c59-4933-b120-f84efa81d0d2"
          }
        },
        {
          "app.user_data.DialogueMessage.cData": {
            "_Index": 14,
            "_Voice": 74,
            "_AirouVoice": 0,
            "_MessageText": "bdc8dd91-99ae-40c9-b93e-b070fd750c1a",
            "_MessageTextChoice": "00000000-0000-0000-0000-000000000000"
          }
        },
        {
          "app.user_data.DialogueMessage.cData": {
            "_Index": 15,
            "_Voice": 0,
            "_AirouVoice": 0,
            "_MessageText": "fd2107b3-c973-44a7-b208-efec3a202171",
            "_MessageTextChoice": "00000000-0000-0000-0000-000000000000"
          }
        }
      ],
      "_ExValues": []
    }
  }
]